smartschool3/Smartschool3.py
smartschool3/__init__.py
smartschool3-1.0.7.dist-info/LICENSE
smartschool3-1.0.7.dist-info/METADATA
smartschool3-1.0.7.dist-info/WHEEL
smartschool3-1.0.7.dist-info/top_level.txt
smartschool3-1.0.7.dist-info/RECORD
