Metadata-Version: 2.1
Name: smartschool3
Version: 1.0.7
Summary: A third-party API for Smartschool
Author: bimsie20
Requires-Python: >=3.7, <4
License-File: LICENSE
Requires-Dist: requests
Requires-Dist: beautifulsoup4
